pins_lib/__init__.py
pins_lib/pins.py
pins_lib-0.0.1.dist-info/METADATA
pins_lib-0.0.1.dist-info/WHEEL
pins_lib-0.0.1.dist-info/top_level.txt
pins_lib-0.0.1.dist-info/RECORD
