Metadata-Version: 2.1
Name: pins-lib
Version: 0.0.1
Summary: The Pin Remapping Library for the DualMCU ONE board ensures compatibility with Arduino shields when using MicroPython.
Author: Mrju10
Author-email: name@email.com
License: License
